{
  "timestamp": 1773037293438,
  "image_point_start": [
    317,
    232
  ],
  "image_point_end": [
    464,
    231
  ],
  "lidar_angle_min": -0.0625,
  "lidar_angle_max": 9.671875,
  "lidar_points_count": 8,
  "avg_distance": 1840.8125,
  "mapped_points": [
    {
      "angle": -0.0625,
      "distance": 1874.0,
      "pixel_x": 317,
      "pixel_y": 232
    },
    {
      "angle": 1.359375,
      "distance": 1862.25,
      "pixel_x": 338,
      "pixel_y": 231
    },
    {
      "angle": 2.734375,
      "distance": 1852.0,
      "pixel_x": 359,
      "pixel_y": 231
    },
    {
      "angle": 4.125,
      "distance": 1843.0,
      "pixel_x": 380,
      "pixel_y": 231
    },
    {
      "angle": 5.53125,
      "distance": 1834.25,
      "pixel_x": 401,
      "pixel_y": 231
    },
    {
      "angle": 6.890625,
      "distance": 1825.25,
      "pixel_x": 422,
      "pixel_y": 231
    },
    {
      "angle": 8.3125,
      "distance": 1819.75,
      "pixel_x": 443,
      "pixel_y": 231
    },
    {
      "angle": 9.671875,
      "distance": 1816.0,
      "pixel_x": 464,
      "pixel_y": 231
    }
  ]
}